{
    "._heidelbermartines_C5H-IMLgGTo.webp": {
        "imagen": "._heidelbermartines_C5H-IMLgGTo.webp",
        "etiquetas": [],
        "Animales": 0,
        "Comida": 0,
        "Turismo": 0,
        "Sonrisa": 0,
        "Grupo de Personas": 0,
        "Perro": 0,
        "Gato": 0,
        "Niños": 0,
        "Adultos": 0,
        "Jóvenes": 0,
        "Deportes": 0,
        "Moda": 0
    },
    "._heidelbermartines_C5W6x5zJM3_.webp": {
        "imagen": "._heidelbermartines_C5W6x5zJM3_.webp",
        "etiquetas": [],
        "Animales": 0,
        "Comida": 0,
        "Turismo": 0,
        "Sonrisa": 0,
        "Grupo de Personas": 0,
        "Perro": 0,
        "Gato": 0,
        "Niños": 0,
        "Adultos": 0,
        "Jóvenes": 0,
        "Deportes": 0,
        "Moda": 0
    },
    "._heidelbermartines_Ci6D8aIJ-lJ.webp": {
        "imagen": "._heidelbermartines_Ci6D8aIJ-lJ.webp",
        "etiquetas": [],
        "Animales": 0,
        "Comida": 0,
        "Turismo": 0,
        "Sonrisa": 0,
        "Grupo de Personas": 0,
        "Perro": 0,
        "Gato": 0,
        "Niños": 0,
        "Adultos": 0,
        "Jóvenes": 0,
        "Deportes": 0,
        "Moda": 0
    },
    "._heidelbermartines_CillC7nJHNF.webp": {
        "imagen": "._heidelbermartines_CillC7nJHNF.webp",
        "etiquetas": [],
        "Animales": 0,
        "Comida": 0,
        "Turismo": 0,
        "Sonrisa": 0,
        "Grupo de Personas": 0,
        "Perro": 0,
        "Gato": 0,
        "Niños": 0,
        "Adultos": 0,
        "Jóvenes": 0,
        "Deportes": 0,
        "Moda": 0
    },
    "._heidelbermartines_CjGd5FjJa5U.webp": {
        "imagen": "._heidelbermartines_CjGd5FjJa5U.webp",
        "etiquetas": [],
        "Animales": 0,
        "Comida": 0,
        "Turismo": 0,
        "Sonrisa": 0,
        "Grupo de Personas": 0,
        "Perro": 0,
        "Gato": 0,
        "Niños": 0,
        "Adultos": 0,
        "Jóvenes": 0,
        "Deportes": 0,
        "Moda": 0
    },
    "._heidelbermartines_CjiX51OgKNb.webp": {
        "imagen": "._heidelbermartines_CjiX51OgKNb.webp",
        "etiquetas": [],
        "Animales": 0,
        "Comida": 0,
        "Turismo": 0,
        "Sonrisa": 0,
        "Grupo de Personas": 0,
        "Perro": 0,
        "Gato": 0,
        "Niños": 0,
        "Adultos": 0,
        "Jóvenes": 0,
        "Deportes": 0,
        "Moda": 0
    },
    "._heidelbermartines_Ck1rwHQJ9PZ.webp": {
        "imagen": "._heidelbermartines_Ck1rwHQJ9PZ.webp",
        "etiquetas": [],
        "Animales": 0,
        "Comida": 0,
        "Turismo": 0,
        "Sonrisa": 0,
        "Grupo de Personas": 0,
        "Perro": 0,
        "Gato": 0,
        "Niños": 0,
        "Adultos": 0,
        "Jóvenes": 0,
        "Deportes": 0,
        "Moda": 0
    },
    "._heidelbermartines_CkCnLYsOf9W.webp": {
        "imagen": "._heidelbermartines_CkCnLYsOf9W.webp",
        "etiquetas": [],
        "Animales": 0,
        "Comida": 0,
        "Turismo": 0,
        "Sonrisa": 0,
        "Grupo de Personas": 0,
        "Perro": 0,
        "Gato": 0,
        "Niños": 0,
        "Adultos": 0,
        "Jóvenes": 0,
        "Deportes": 0,
        "Moda": 0
    },
    "._heidelbermartines_CkCtEQtOHuj.webp": {
        "imagen": "._heidelbermartines_CkCtEQtOHuj.webp",
        "etiquetas": [],
        "Animales": 0,
        "Comida": 0,
        "Turismo": 0,
        "Sonrisa": 0,
        "Grupo de Personas": 0,
        "Perro": 0,
        "Gato": 0,
        "Niños": 0,
        "Adultos": 0,
        "Jóvenes": 0,
        "Deportes": 0,
        "Moda": 0
    },
    "._heidelbermartines_CkeRJiGpDDj.webp": {
        "imagen": "._heidelbermartines_CkeRJiGpDDj.webp",
        "etiquetas": [],
        "Animales": 0,
        "Comida": 0,
        "Turismo": 0,
        "Sonrisa": 0,
        "Grupo de Personas": 0,
        "Perro": 0,
        "Gato": 0,
        "Niños": 0,
        "Adultos": 0,
        "Jóvenes": 0,
        "Deportes": 0,
        "Moda": 0
    },
    "._heidelbermartines_CkhahoYOvnV.webp": {
        "imagen": "._heidelbermartines_CkhahoYOvnV.webp",
        "etiquetas": [],
        "Animales": 0,
        "Comida": 0,
        "Turismo": 0,
        "Sonrisa": 0,
        "Grupo de Personas": 0,
        "Perro": 0,
        "Gato": 0,
        "Niños": 0,
        "Adultos": 0,
        "Jóvenes": 0,
        "Deportes": 0,
        "Moda": 0
    },
    "._heidelbermartines_Cki3MQ7JNEj.webp": {
        "imagen": "._heidelbermartines_Cki3MQ7JNEj.webp",
        "etiquetas": [],
        "Animales": 0,
        "Comida": 0,
        "Turismo": 0,
        "Sonrisa": 0,
        "Grupo de Personas": 0,
        "Perro": 0,
        "Gato": 0,
        "Niños": 0,
        "Adultos": 0,
        "Jóvenes": 0,
        "Deportes": 0,
        "Moda": 0
    },
    "._heidelbermartines_CkmqulSu7SI.webp": {
        "imagen": "._heidelbermartines_CkmqulSu7SI.webp",
        "etiquetas": [],
        "Animales": 0,
        "Comida": 0,
        "Turismo": 0,
        "Sonrisa": 0,
        "Grupo de Personas": 0,
        "Perro": 0,
        "Gato": 0,
        "Niños": 0,
        "Adultos": 0,
        "Jóvenes": 0,
        "Deportes": 0,
        "Moda": 0
    },
    "._heidelbermartines_ClCmjrtJupu.webp": {
        "imagen": "._heidelbermartines_ClCmjrtJupu.webp",
        "etiquetas": [],
        "Animales": 0,
        "Comida": 0,
        "Turismo": 0,
        "Sonrisa": 0,
        "Grupo de Personas": 0,
        "Perro": 0,
        "Gato": 0,
        "Niños": 0,
        "Adultos": 0,
        "Jóvenes": 0,
        "Deportes": 0,
        "Moda": 0
    },
    "._heidelbermartines_ClMrBXJp0_0.webp": {
        "imagen": "._heidelbermartines_ClMrBXJp0_0.webp",
        "etiquetas": [],
        "Animales": 0,
        "Comida": 0,
        "Turismo": 0,
        "Sonrisa": 0,
        "Grupo de Personas": 0,
        "Perro": 0,
        "Gato": 0,
        "Niños": 0,
        "Adultos": 0,
        "Jóvenes": 0,
        "Deportes": 0,
        "Moda": 0
    },
    "._heidelbermartines_ClQKHC-OVfL.webp": {
        "imagen": "._heidelbermartines_ClQKHC-OVfL.webp",
        "etiquetas": [],
        "Animales": 0,
        "Comida": 0,
        "Turismo": 0,
        "Sonrisa": 0,
        "Grupo de Personas": 0,
        "Perro": 0,
        "Gato": 0,
        "Niños": 0,
        "Adultos": 0,
        "Jóvenes": 0,
        "Deportes": 0,
        "Moda": 0
    },
    "._heidelbermartines_ClSYAZLumK9.webp": {
        "imagen": "._heidelbermartines_ClSYAZLumK9.webp",
        "etiquetas": [],
        "Animales": 0,
        "Comida": 0,
        "Turismo": 0,
        "Sonrisa": 0,
        "Grupo de Personas": 0,
        "Perro": 0,
        "Gato": 0,
        "Niños": 0,
        "Adultos": 0,
        "Jóvenes": 0,
        "Deportes": 0,
        "Moda": 0
    },
    "._heidelbermartines_ClUa9zTpu4B.webp": {
        "imagen": "._heidelbermartines_ClUa9zTpu4B.webp",
        "etiquetas": [],
        "Animales": 0,
        "Comida": 0,
        "Turismo": 0,
        "Sonrisa": 0,
        "Grupo de Personas": 0,
        "Perro": 0,
        "Gato": 0,
        "Niños": 0,
        "Adultos": 0,
        "Jóvenes": 0,
        "Deportes": 0,
        "Moda": 0
    },
    "._heidelbermartines_ClUbGMap7Pi.webp": {
        "imagen": "._heidelbermartines_ClUbGMap7Pi.webp",
        "etiquetas": [],
        "Animales": 0,
        "Comida": 0,
        "Turismo": 0,
        "Sonrisa": 0,
        "Grupo de Personas": 0,
        "Perro": 0,
        "Gato": 0,
        "Niños": 0,
        "Adultos": 0,
        "Jóvenes": 0,
        "Deportes": 0,
        "Moda": 0
    },
    "._heidelbermartines_ClugWmlJDEp.webp": {
        "imagen": "._heidelbermartines_ClugWmlJDEp.webp",
        "etiquetas": [],
        "Animales": 0,
        "Comida": 0,
        "Turismo": 0,
        "Sonrisa": 0,
        "Grupo de Personas": 0,
        "Perro": 0,
        "Gato": 0,
        "Niños": 0,
        "Adultos": 0,
        "Jóvenes": 0,
        "Deportes": 0,
        "Moda": 0
    },
    "heidelbermartines_C5H-IMLgGTo.webp": {
        "imagen": "heidelbermartines_C5H-IMLgGTo.webp",
        "etiquetas": [
            "eyewear",
            "glasses",
            "vision care",
            "sunglasses",
            "nose",
            "hat",
            "headgear",
            "goggles",
            "cap",
            "baseball cap"
        ],
        "Animales": 0,
        "Comida": 0,
        "Turismo": 0,
        "Sonrisa": 0,
        "Grupo de Personas": 0,
        "Perro": 0,
        "Gato": 0,
        "Niños": 0,
        "Adultos": 0,
        "Jóvenes": 0,
        "Deportes": 0,
        "Moda": 0
    },
    "heidelbermartines_C5W6x5zJM3_.webp": {
        "imagen": "heidelbermartines_C5W6x5zJM3_.webp",
        "etiquetas": [
            "selfie",
            "happiness",
            "sunglasses"
        ],
        "Animales": 0,
        "Comida": 0,
        "Turismo": 0,
        "Sonrisa": 0,
        "Grupo de Personas": 0,
        "Perro": 0,
        "Gato": 0,
        "Niños": 0,
        "Adultos": 0,
        "Jóvenes": 0,
        "Deportes": 0,
        "Moda": 0
    },
    "heidelbermartines_Ci6D8aIJ-lJ.webp": {
        "imagen": "heidelbermartines_Ci6D8aIJ-lJ.webp",
        "etiquetas": [
            "food",
            "ingredient",
            "tableware",
            "seafood",
            "cookware and bakeware",
            "recipe",
            "cooking",
            "rice",
            "bivalvia",
            "staple food"
        ],
        "Animales": 0,
        "Comida": 1,
        "Turismo": 0,
        "Sonrisa": 0,
        "Grupo de Personas": 0,
        "Perro": 0,
        "Gato": 0,
        "Niños": 0,
        "Adultos": 0,
        "Jóvenes": 0,
        "Deportes": 0,
        "Moda": 0
    },
    "heidelbermartines_CillC7nJHNF.webp": {
        "imagen": "heidelbermartines_CillC7nJHNF.webp",
        "etiquetas": [
            "cylinder",
            "steel",
            "aluminium"
        ],
        "Animales": 0,
        "Comida": 0,
        "Turismo": 0,
        "Sonrisa": 0,
        "Grupo de Personas": 0,
        "Perro": 0,
        "Gato": 0,
        "Niños": 0,
        "Adultos": 0,
        "Jóvenes": 0,
        "Deportes": 0,
        "Moda": 0
    },
    "heidelbermartines_CjGd5FjJa5U.webp": {
        "imagen": "heidelbermartines_CjGd5FjJa5U.webp",
        "etiquetas": [
            "eyewear",
            "glasses",
            "sunglasses",
            "vision care",
            "face",
            "nose",
            "goggles",
            "summer",
            "headgear",
            "personal protective equipment"
        ],
        "Animales": 0,
        "Comida": 0,
        "Turismo": 0,
        "Sonrisa": 0,
        "Grupo de Personas": 0,
        "Perro": 0,
        "Gato": 0,
        "Niños": 0,
        "Adultos": 0,
        "Jóvenes": 0,
        "Deportes": 0,
        "Moda": 0
    },
    "heidelbermartines_CjiX51OgKNb.webp": {
        "imagen": "heidelbermartines_CjiX51OgKNb.webp",
        "etiquetas": [
            "sleeve",
            "shoulder",
            "neck",
            "active shirt",
            "buzz cut",
            "crew cut",
            "selfie",
            "high and tight",
            "happiness",
            "mobile phone"
        ],
        "Animales": 0,
        "Comida": 0,
        "Turismo": 0,
        "Sonrisa": 0,
        "Grupo de Personas": 0,
        "Perro": 0,
        "Gato": 0,
        "Niños": 0,
        "Adultos": 0,
        "Jóvenes": 0,
        "Deportes": 0,
        "Moda": 0
    },
    "heidelbermartines_Ck1rwHQJ9PZ.webp": {
        "imagen": "heidelbermartines_Ck1rwHQJ9PZ.webp",
        "etiquetas": [
            "eyewear",
            "sunglasses",
            "glasses",
            "vision care",
            "goggles",
            "personal protective equipment",
            "summer",
            "black hair",
            "selfie",
            "vacation"
        ],
        "Animales": 0,
        "Comida": 0,
        "Turismo": 1,
        "Sonrisa": 0,
        "Grupo de Personas": 0,
        "Perro": 0,
        "Gato": 0,
        "Niños": 0,
        "Adultos": 0,
        "Jóvenes": 0,
        "Deportes": 0,
        "Moda": 0
    },
    "heidelbermartines_CkCnLYsOf9W.webp": {
        "imagen": "heidelbermartines_CkCnLYsOf9W.webp",
        "etiquetas": [
            "eyewear",
            "sunglasses",
            "glasses",
            "vision care",
            "goggles",
            "black hair",
            "selfie",
            "mobile phone",
            "gadget",
            "active shirt"
        ],
        "Animales": 0,
        "Comida": 0,
        "Turismo": 0,
        "Sonrisa": 0,
        "Grupo de Personas": 0,
        "Perro": 0,
        "Gato": 0,
        "Niños": 0,
        "Adultos": 0,
        "Jóvenes": 0,
        "Deportes": 0,
        "Moda": 0
    },
    "heidelbermartines_CkCtEQtOHuj.webp": {
        "imagen": "heidelbermartines_CkCtEQtOHuj.webp",
        "etiquetas": [
            "chordophone",
            "string instrument"
        ],
        "Animales": 0,
        "Comida": 0,
        "Turismo": 0,
        "Sonrisa": 0,
        "Grupo de Personas": 0,
        "Perro": 0,
        "Gato": 0,
        "Niños": 0,
        "Adultos": 0,
        "Jóvenes": 0,
        "Deportes": 0,
        "Moda": 0
    },
    "heidelbermartines_CkeRJiGpDDj.webp": {
        "imagen": "heidelbermartines_CkeRJiGpDDj.webp",
        "etiquetas": [
            "food",
            "salad",
            "ingredient",
            "seafood",
            "vegetable",
            "recipe",
            "leaf vegetable",
            "garnish",
            "culinary arts",
            "shrimp"
        ],
        "Animales": 0,
        "Comida": 1,
        "Turismo": 0,
        "Sonrisa": 0,
        "Grupo de Personas": 0,
        "Perro": 0,
        "Gato": 0,
        "Niños": 0,
        "Adultos": 0,
        "Jóvenes": 0,
        "Deportes": 0,
        "Moda": 0
    },
    "heidelbermartines_CkhahoYOvnV.webp": {
        "imagen": "heidelbermartines_CkhahoYOvnV.webp",
        "etiquetas": [
            "food",
            "rice",
            "recipe",
            "staple food",
            "breakfast",
            "produce",
            "cooking banana",
            "fruit",
            "side dish",
            "bananas"
        ],
        "Animales": 0,
        "Comida": 1,
        "Turismo": 0,
        "Sonrisa": 0,
        "Grupo de Personas": 0,
        "Perro": 0,
        "Gato": 0,
        "Niños": 0,
        "Adultos": 0,
        "Jóvenes": 0,
        "Deportes": 0,
        "Moda": 0
    },
    "heidelbermartines_Cki3MQ7JNEj.webp": {
        "imagen": "heidelbermartines_Cki3MQ7JNEj.webp",
        "etiquetas": [
            "eyewear",
            "sunglasses",
            "glasses",
            "watch",
            "vision care",
            "goggles",
            "personal protective equipment",
            "wrist",
            "analog watch",
            "active shirt"
        ],
        "Animales": 0,
        "Comida": 0,
        "Turismo": 0,
        "Sonrisa": 0,
        "Grupo de Personas": 0,
        "Perro": 0,
        "Gato": 0,
        "Niños": 0,
        "Adultos": 0,
        "Jóvenes": 0,
        "Deportes": 0,
        "Moda": 0
    },
    "heidelbermartines_CkmqulSu7SI.webp": {
        "imagen": "heidelbermartines_CkmqulSu7SI.webp",
        "etiquetas": [
            "smile",
            "cheek",
            "happiness",
            "eyebrow",
            "lips",
            "forehead",
            "jaw",
            "mouth",
            "black hair",
            "facial expression"
        ],
        "Animales": 0,
        "Comida": 0,
        "Turismo": 0,
        "Sonrisa": 1,
        "Grupo de Personas": 0,
        "Perro": 0,
        "Gato": 0,
        "Niños": 0,
        "Adultos": 0,
        "Jóvenes": 0,
        "Deportes": 0,
        "Moda": 0
    },
    "heidelbermartines_ClCmjrtJupu.webp": {
        "imagen": "heidelbermartines_ClCmjrtJupu.webp",
        "etiquetas": [
            "motor vehicle",
            "automotive tire",
            "commercial vehicle",
            "automotive lighting",
            "automotive wheel system",
            "grille",
            "freight transport",
            "truck",
            "machine",
            "fender"
        ],
        "Animales": 0,
        "Comida": 0,
        "Turismo": 0,
        "Sonrisa": 0,
        "Grupo de Personas": 0,
        "Perro": 0,
        "Gato": 0,
        "Niños": 0,
        "Adultos": 0,
        "Jóvenes": 0,
        "Deportes": 0,
        "Moda": 0
    },
    "heidelbermartines_ClMrBXJp0_0.webp": {
        "imagen": "heidelbermartines_ClMrBXJp0_0.webp",
        "etiquetas": [
            "eyewear",
            "glasses",
            "vision care",
            "hat",
            "sunglasses",
            "headgear",
            "cap",
            "goggles",
            "baseball cap",
            "sun hat"
        ],
        "Animales": 0,
        "Comida": 0,
        "Turismo": 0,
        "Sonrisa": 0,
        "Grupo de Personas": 0,
        "Perro": 0,
        "Gato": 0,
        "Niños": 0,
        "Adultos": 0,
        "Jóvenes": 0,
        "Deportes": 0,
        "Moda": 0
    },
    "heidelbermartines_ClQKHC-OVfL.webp": {
        "imagen": "heidelbermartines_ClQKHC-OVfL.webp",
        "etiquetas": [
            "chin",
            "cheek",
            "eyebrow",
            "forehead",
            "skin",
            "jaw",
            "child",
            "neck",
            "eyelash",
            "facial expression"
        ],
        "Animales": 0,
        "Comida": 0,
        "Turismo": 0,
        "Sonrisa": 0,
        "Grupo de Personas": 0,
        "Perro": 0,
        "Gato": 0,
        "Niños": 1,
        "Adultos": 0,
        "Jóvenes": 0,
        "Deportes": 0,
        "Moda": 0
    },
    "heidelbermartines_ClSYAZLumK9.webp": {
        "imagen": "heidelbermartines_ClSYAZLumK9.webp",
        "etiquetas": [
            "hat",
            "headgear",
            "cap",
            "baseball cap",
            "selfie",
            "logo",
            "facial hair",
            "cricket cap",
            "active shirt"
        ],
        "Animales": 0,
        "Comida": 0,
        "Turismo": 0,
        "Sonrisa": 0,
        "Grupo de Personas": 0,
        "Perro": 0,
        "Gato": 0,
        "Niños": 0,
        "Adultos": 0,
        "Jóvenes": 0,
        "Deportes": 0,
        "Moda": 0
    },
    "heidelbermartines_ClUa9zTpu4B.webp": {
        "imagen": "heidelbermartines_ClUa9zTpu4B.webp",
        "etiquetas": [
            "eyewear",
            "glasses",
            "vision care",
            "sunglasses",
            "goggles",
            "headgear",
            "hat",
            "personal protective equipment",
            "cap",
            "active shirt"
        ],
        "Animales": 0,
        "Comida": 0,
        "Turismo": 0,
        "Sonrisa": 0,
        "Grupo de Personas": 0,
        "Perro": 0,
        "Gato": 0,
        "Niños": 0,
        "Adultos": 0,
        "Jóvenes": 0,
        "Deportes": 0,
        "Moda": 0
    },
    "heidelbermartines_ClUbGMap7Pi.webp": {
        "imagen": "heidelbermartines_ClUbGMap7Pi.webp",
        "etiquetas": [
            "eyewear",
            "glasses",
            "vision care",
            "sunglasses",
            "goggles",
            "cap",
            "hat",
            "active shirt",
            "baseball cap",
            "selfie"
        ],
        "Animales": 0,
        "Comida": 0,
        "Turismo": 0,
        "Sonrisa": 0,
        "Grupo de Personas": 0,
        "Perro": 0,
        "Gato": 0,
        "Niños": 0,
        "Adultos": 0,
        "Jóvenes": 0,
        "Deportes": 0,
        "Moda": 0
    },
    "heidelbermartines_ClugWmlJDEp.webp": {
        "imagen": "heidelbermartines_ClugWmlJDEp.webp",
        "etiquetas": [
            "food",
            "tableware",
            "ingredient",
            "vegetable",
            "dishware",
            "recipe",
            "plate",
            "garnish",
            "seafood",
            "culinary arts"
        ],
        "Animales": 0,
        "Comida": 1,
        "Turismo": 0,
        "Sonrisa": 0,
        "Grupo de Personas": 0,
        "Perro": 0,
        "Gato": 0,
        "Niños": 0,
        "Adultos": 0,
        "Jóvenes": 0,
        "Deportes": 0,
        "Moda": 0
    }
}