{
    "all.salazar3_C-ormq9uVPy.webp": {
        "imagen": "all.salazar3_C-ormq9uVPy.webp",
        "etiquetas": [
            "sidewalk",
            "carnivores",
            "shadow",
            "walkway",
            "walking",
            "canidae"
        ],
        "Animales": 0,
        "Comida": 0,
        "Turismo": 0,
        "Sonrisa": 0,
        "Grupo de Personas": 0,
        "Perro": 0,
        "Gato": 0,
        "Niños": 0,
        "Adultos": 0,
        "Jóvenes": 0,
        "Deportes": 0,
        "Moda": 0
    },
    "all.salazar3_C3LuXYKOr-s.webp": {
        "imagen": "all.salazar3_C3LuXYKOr-s.webp",
        "etiquetas": [
            "dog",
            "carnivores",
            "snout",
            "collar",
            "working animal",
            "canidae",
            "fur",
            "herding dog",
            "pet supply",
            "stairs"
        ],
        "Animales": 0,
        "Comida": 0,
        "Turismo": 0,
        "Sonrisa": 0,
        "Grupo de Personas": 0,
        "Perro": 1,
        "Gato": 0,
        "Niños": 0,
        "Adultos": 0,
        "Jóvenes": 0,
        "Deportes": 0,
        "Moda": 0
    },
    "all.salazar3_C3LuXYKOr-s_2.webp": {
        "imagen": "all.salazar3_C3LuXYKOr-s_2.webp",
        "etiquetas": [
            "glass",
            "daylighting",
            "lens flare"
        ],
        "Animales": 0,
        "Comida": 0,
        "Turismo": 0,
        "Sonrisa": 0,
        "Grupo de Personas": 0,
        "Perro": 0,
        "Gato": 0,
        "Niños": 0,
        "Adultos": 0,
        "Jóvenes": 0,
        "Deportes": 0,
        "Moda": 0
    },
    "all.salazar3_C3LuXYKOr-s_3.webp": {
        "imagen": "all.salazar3_C3LuXYKOr-s_3.webp",
        "etiquetas": [
            "dog",
            "carnivores",
            "snout",
            "working animal",
            "terrestrial animal",
            "canidae",
            "herding dog",
            "collar",
            "fur",
            "pet supply"
        ],
        "Animales": 0,
        "Comida": 0,
        "Turismo": 0,
        "Sonrisa": 0,
        "Grupo de Personas": 0,
        "Perro": 1,
        "Gato": 0,
        "Niños": 0,
        "Adultos": 0,
        "Jóvenes": 0,
        "Deportes": 0,
        "Moda": 0
    },
    "all.salazar3_CemBfNOu-Zi.webp": {
        "imagen": "all.salazar3_CemBfNOu-Zi.webp",
        "etiquetas": [
            "eyewear",
            "glasses",
            "vision care",
            "facial hair",
            "beard",
            "moustache",
            "smoke",
            "cap",
            "smoking",
            "goggles"
        ],
        "Animales": 0,
        "Comida": 0,
        "Turismo": 0,
        "Sonrisa": 0,
        "Grupo de Personas": 0,
        "Perro": 0,
        "Gato": 0,
        "Niños": 0,
        "Adultos": 0,
        "Jóvenes": 0,
        "Deportes": 0,
        "Moda": 0
    },
    "all.salazar3_CemBfNOu-Zi_2.webp": {
        "imagen": "all.salazar3_CemBfNOu-Zi_2.webp",
        "etiquetas": [
            "road",
            "asphalt",
            "street",
            "cap",
            "travel",
            "overhead power line",
            "baseball cap",
            "road trip",
            "traffic"
        ],
        "Animales": 0,
        "Comida": 0,
        "Turismo": 1,
        "Sonrisa": 0,
        "Grupo de Personas": 0,
        "Perro": 0,
        "Gato": 0,
        "Niños": 0,
        "Adultos": 0,
        "Jóvenes": 0,
        "Deportes": 0,
        "Moda": 0
    },
    "all.salazar3_CfJAKGtubz-.webp": {
        "imagen": "all.salazar3_CfJAKGtubz-.webp",
        "etiquetas": [
            "dog",
            "carnivores",
            "vertebrate",
            "german shepherd",
            "snout",
            "old german shepherd dog",
            "working animal",
            "king shepherd",
            "fur",
            "canidae"
        ],
        "Animales": 0,
        "Comida": 0,
        "Turismo": 0,
        "Sonrisa": 0,
        "Grupo de Personas": 0,
        "Perro": 1,
        "Gato": 0,
        "Niños": 0,
        "Adultos": 0,
        "Jóvenes": 0,
        "Deportes": 0,
        "Moda": 0
    },
    "all.salazar3_CsDWtRAO0we.webp": {
        "imagen": "all.salazar3_CsDWtRAO0we.webp",
        "etiquetas": [
            "eyewear",
            "photograph",
            "glasses",
            "vision care",
            "white",
            "monochrome photography",
            "headgear",
            "cap",
            "hat",
            "black and white"
        ],
        "Animales": 0,
        "Comida": 0,
        "Turismo": 0,
        "Sonrisa": 0,
        "Grupo de Personas": 0,
        "Perro": 0,
        "Gato": 0,
        "Niños": 0,
        "Adultos": 0,
        "Jóvenes": 0,
        "Deportes": 0,
        "Moda": 0
    },
    "all.salazar3_CtCtrTSOvsC.webp": {
        "imagen": "all.salazar3_CtCtrTSOvsC.webp",
        "etiquetas": [
            "blue",
            "chin",
            "cheek",
            "face",
            "nose",
            "eye",
            "facial expression",
            "child",
            "black hair",
            "baby & toddler clothing"
        ],
        "Animales": 0,
        "Comida": 0,
        "Turismo": 0,
        "Sonrisa": 0,
        "Grupo de Personas": 0,
        "Perro": 0,
        "Gato": 0,
        "Niños": 1,
        "Adultos": 0,
        "Jóvenes": 0,
        "Deportes": 0,
        "Moda": 0
    },
    "all.salazar3_CtCuhY3O9PR.webp": {
        "imagen": "all.salazar3_CtCuhY3O9PR.webp",
        "etiquetas": [
            "standing",
            "summer",
            "bermuda shorts",
            "leisure",
            "vacation",
            "calf"
        ],
        "Animales": 0,
        "Comida": 0,
        "Turismo": 1,
        "Sonrisa": 0,
        "Grupo de Personas": 0,
        "Perro": 0,
        "Gato": 0,
        "Niños": 0,
        "Adultos": 0,
        "Jóvenes": 0,
        "Deportes": 0,
        "Moda": 0
    },
    "all.salazar3_CtNYjFjOoUY.webp": {
        "imagen": "all.salazar3_CtNYjFjOoUY.webp",
        "etiquetas": [
            "happiness",
            "smile",
            "sitting",
            "fun",
            "leisure",
            "child",
            "comfort",
            "lap",
            "toddler",
            "outdoor furniture"
        ],
        "Animales": 0,
        "Comida": 0,
        "Turismo": 0,
        "Sonrisa": 1,
        "Grupo de Personas": 0,
        "Perro": 0,
        "Gato": 0,
        "Niños": 1,
        "Adultos": 0,
        "Jóvenes": 0,
        "Deportes": 0,
        "Moda": 0
    },
    "all.salazar3_Czpn0wWOV0K.webp": {
        "imagen": "all.salazar3_Czpn0wWOV0K.webp",
        "etiquetas": [
            "dog",
            "field",
            "canidae",
            "meteorological phenomenon",
            "cumulus",
            "herding dog"
        ],
        "Animales": 0,
        "Comida": 0,
        "Turismo": 0,
        "Sonrisa": 0,
        "Grupo de Personas": 0,
        "Perro": 1,
        "Gato": 0,
        "Niños": 0,
        "Adultos": 0,
        "Jóvenes": 0,
        "Deportes": 0,
        "Moda": 0
    },
    "all.salazar3_CzxAdGHLc9e.webp": {
        "imagen": "all.salazar3_CzxAdGHLc9e.webp",
        "etiquetas": [
            "dog",
            "carnivores",
            "german shepherd",
            "working animal",
            "snout",
            "old german shepherd dog",
            "canidae",
            "king shepherd",
            "pet supply",
            "herding dog"
        ],
        "Animales": 0,
        "Comida": 0,
        "Turismo": 0,
        "Sonrisa": 0,
        "Grupo de Personas": 0,
        "Perro": 1,
        "Gato": 0,
        "Niños": 0,
        "Adultos": 0,
        "Jóvenes": 0,
        "Deportes": 0,
        "Moda": 0
    }
}